cloudscraper/__init__.py
cloudscraper/cloudflare.py
cloudscraper/exceptions.py
cloudscraper/help.py
cloudscraper/captcha/2captcha.py
cloudscraper/captcha/9kw.py
cloudscraper/captcha/__init__.py
cloudscraper/captcha/anticaptcha.py
cloudscraper/captcha/capmonster.py
cloudscraper/captcha/capsolver.py
cloudscraper/captcha/deathbycaptcha.py
cloudscraper/interpreters/__init__.py
cloudscraper/interpreters/chakracore.py
cloudscraper/interpreters/encapsulated.py
cloudscraper/interpreters/js2py.py
cloudscraper/interpreters/jsunfuck.py
cloudscraper/interpreters/native.py
cloudscraper/interpreters/nodejs.py
cloudscraper/interpreters/v8.py
cloudscraper/user_agent/__init__.py
cloudscraper/user_agent/browsers.json
cloudscraper-1.2.70.dist-info/LICENSE
cloudscraper-1.2.70.dist-info/METADATA
cloudscraper-1.2.70.dist-info/WHEEL
cloudscraper-1.2.70.dist-info/top_level.txt
cloudscraper-1.2.70.dist-info/RECORD
