Metadata-Version: 2.1
Name: cloudscraper
Version: 1.2.70
Summary: A Python module to bypass Cloudflare's anti-bot page.
Home-page: https://github.com/venomous/cloudscraper
Author: VeNoMouS
Author-email: venom@gen-x.co.nz
License: UNKNOWN
Keywords: cloudflare,scraping,ddos,scrape,webscraper,anti-bot,waf,iuam,bypass,challenge
Platform: UNKNOWN
Classifier: Development Status :: 5 - Production/Stable
Classifier: Intended Audience :: Developers
Classifier: Natural Language :: English
Classifier: License :: OSI Approved :: MIT License
Classifier: Operating System :: OS Independent
Classifier: Programming Language :: Python
Classifier: Programming Language :: Python :: 3
Classifier: Programming Language :: Python :: 3.6
Classifier: Programming Language :: Python :: 3.7
Classifier: Programming Language :: Python :: 3.8
Classifier: Programming Language :: Python :: 3.9
Classifier: Topic :: Internet :: WWW/HTTP
Classifier: Topic :: Software Development :: Libraries :: Application Frameworks
Classifier: Topic :: Software Development :: Libraries :: Python Modules
Requires-Dist: pyparsing (>=2.4.7)
Requires-Dist: requests (>=2.9.2)
Requires-Dist: requests-toolbelt (>=0.9.1)
